python_ufile/__init__.py
python_ufile/python_ufile.py
python_ufile-1.0.0.dist-info/AUTHORS.rst
python_ufile-1.0.0.dist-info/LICENSE
python_ufile-1.0.0.dist-info/METADATA
python_ufile-1.0.0.dist-info/WHEEL
python_ufile-1.0.0.dist-info/top_level.txt
python_ufile-1.0.0.dist-info/RECORD
