Metadata-Version: 2.1
Name: python-ufile
Version: 1.0.0
Summary: Upload/Download from ufile.io with this minimal python sdk.
Home-page: https://github.com/AriaBagheri/python_ufile
Author: Aria Bagheri
Author-email: Aria Bagheri <ariab9342@gmail.com>
License: MIT License        
Project-URL: Homepage, https://github.com/AriaBagheri/python_ufile
Keywords: ufile.io,upload,download
Classifier: License :: OSI Approved :: MIT License
Classifier: Programming Language :: Python
Classifier: Programming Language :: Python :: 3
Requires-Python: >=3.6
License-File: LICENSE
License-File: AUTHORS.rst
Requires-Dist: aiofiles (>=0.8.0)
Requires-Dist: requests (>=2.27.1)
